synth_a_py/__init__.py
synth_a_py/base.py
synth_a_py/file.py
synth_a_py/gitignore.py
synth_a_py/ini.py
synth_a_py/license.py
synth_a_py/py.typed
synth_a_py/toml.py
synth_a_py/utils.py
synth_a_py/yaml.py
synth_a_py-1.6.0.dist-info/LICENSE
synth_a_py-1.6.0.dist-info/WHEEL
synth_a_py-1.6.0.dist-info/METADATA
synth_a_py-1.6.0.dist-info/RECORD
